examples/example_interface.py
examples/example_runtime.py
ataraxis_communication_interface/__init__.py
ataraxis_communication_interface/communication.py
ataraxis_communication_interface/mcp_server.py
ataraxis_communication_interface/microcontroller_interface.py
ataraxis_communication_interface/py.typed
ataraxis_communication_interface-4.2.0.dist-info/METADATA
ataraxis_communication_interface-4.2.0.dist-info/WHEEL
ataraxis_communication_interface-4.2.0.dist-info/entry_points.txt
ataraxis_communication_interface-4.2.0.dist-info/licenses/LICENSE
ataraxis_communication_interface-4.2.0.dist-info/RECORD
