Metadata-Version: 2.4
Name: ataraxis-communication-interface
Version: 4.2.0
Summary: Provides the centralized interface for exchanging commands and data between Arduino and Teensy microcontrollers and host-computers.
Project-URL: Homepage, https://github.com/Sun-Lab-NBB/ataraxis-communication-interface
Project-URL: Documentation, https://ataraxis-communication-interface-api.netlify.app/
Author: Ivan Kondratyev, Jacob Groner
Maintainer-email: Ivan Kondratyev <ik278@cornell.edu>
License:                     GNU GENERAL PUBLIC LICENSE
License-File: LICENSE
Keywords: MCP,MQTT,TCP,UART,USB,ataraxis,communication,interface,microcontroller,serial
Classifier: Development Status :: 5 - Production/Stable
Classifier: Intended Audience :: Developers
Classifier: License :: OSI Approved :: GNU General Public License v3 or later (GPLv3+)
Classifier: Operating System :: MacOS :: MacOS X
Classifier: Operating System :: Microsoft :: Windows
Classifier: Operating System :: POSIX :: Linux
Classifier: Programming Language :: Python :: 3.12
Classifier: Programming Language :: Python :: 3.13
Classifier: Programming Language :: Python :: 3.14
Classifier: Topic :: Communications
Classifier: Typing :: Typed
Requires-Python: <3.15,>=3.12
Requires-Dist: ataraxis-base-utilities<6,>=5
Requires-Dist: ataraxis-data-structures<6,>=5
Requires-Dist: ataraxis-time<6,>=5
Requires-Dist: ataraxis-transport-layer-pc<4,>=3.1.1
Requires-Dist: httpx<1,>=0.27
Requires-Dist: mcp<2,>=1
Requires-Dist: numpy<3,>=2
Requires-Dist: paho-mqtt<3,>=2
Requires-Dist: tqdm<5,>=4
Provides-Extra: dev
Requires-Dist: ataraxis-automation<8,>=7; extra == 'dev'
Requires-Dist: tox-uv<2,>=1; extra == 'dev'
Requires-Dist: tox<5,>=4; extra == 'dev'
Requires-Dist: types-paho-mqtt<2,>=1; extra == 'dev'
Requires-Dist: types-pyserial<4,>=3; extra == 'dev'
Requires-Dist: types-tqdm<5,>=4; extra == 'dev'
Requires-Dist: uv<1,>=0; extra == 'dev'
